2023kuec2016/lab2/full_adder.v
module full_adder (
    input a,
    input b,
    input cin,
    output y,
    output cout
);

assign y = a ^ b ^ cin;
assign cout = (a & b) | ((a ^ b) & cin);

endmodule

2023kuec2016/lab2/full_adder_tb.v
`include "full_adder.v"

module full_adder_tb;

reg a, b, cin;
wire y, cout;

full_adder uut (
    .a(a),
    .b(b),
    .cin(cin),
    .y(y),
    .cout(cout)
);

initial begin
    a = 0; b = 0; cin = 0; #5;
    a = 0; b = 0; cin = 1; #5;
    a = 0; b = 1; cin = 0; #5;
    a = 0; b = 1; cin = 1; #5;
    a = 1; b = 0; cin = 0; #5;
    a = 1; b = 0; cin = 1; #5;
    a = 1; b = 1; cin = 0; #5;
    a = 1; b = 1; cin = 1; #5;
    $finish;
end

initial begin
    $dumpfile("full_adder.vcd");
    $dumpvars(0, full_adder_tb);
end

endmodule

2023kuec2016/SarthakSinghTariyal_2023kuec2016_lab2/full_adder.vcd
$date
	Wed Sep 11 10:44:05 2024
$end
$version
	Icarus Verilog
$end
$timescale
	1s
$end
$scope module full_adder_tb $end
$var wire 1 ! y $end
$var wire 1 " cout $end
$var reg 1 # a $end
$var reg 1 $ b $end
$var reg 1 % cin $end
$scope module uut $end
$var wire 1 # a $end
$var wire 1 $ b $end
$var wire 1 % cin $end
$var wire 1 " cout $end
$var wire 1 ! y $end
$upscope $end
$upscope $end
$enddefinitions $end
#0
$dumpvars
0%
0$
0#
0"
0!
$end
#5
1!
1%
#10
0%
1$
#15
1"
0!
1%
#20
0"
1!
0%
0$
1#
#25
1"
0!
1%
#30
0%
1$
#35
1!
1%
