2023kuec2016/lab2/q2.v
module q2 (
    input a,b,c,d,
    output y
);

assign y = ~(a & b) | ~(c & d);

endmodule

2023kuec2016/SarthakSinghTariyal_2023kuec2016_lab2/q2_tb.v
`include "q2.v"

module q2_tb;

reg a, b, c, d;
wire y;

q2 uut (
    .a(a),
    .b(b),
    .c(c),
    .d(d),
    .y(y)
);

initial begin
    a=0;b=0;c=0;d=0;#5;
    a=0;b=0;c=0;d=1;#5; 
    a=0;b=0;c=1;d=0;#5;    
    a=0;b=0;c=1;d=1;#5;    
    a=0;b=1;c=0;d=0;#5;    
    a=0;b=1;c=0;d=1;#5;    
    a=0;b=1;c=1;d=0;#5;    
    a=0;b=1;c=1;d=1;#5;    
    a=1;b=0;c=0;d=0;#5;    
    a=1;b=0;c=0;d=1;#5;    
    a=1;b=0;c=1;d=0;#5;    
    a=1;b=0;c=1;d=1;#5;    
    a=1;b=1;c=0;d=0;#5;    
    a=1;b=1;c=0;d=1;#5;    
    a=1;b=1;c=1;d=0;#5;    
    a=1;b=1;c=1;d=1;#5;    
    $finish;
end

initial begin
    $dumpfile("q2.vcd");
    $dumpvars(0, q2_tb);
end

endmodule

2023kuec2016/SarthakSinghTariyal_2023kuec2016_lab2/q2.vcd
$date
	Wed Sep 11 11:31:54 2024
$end
$version
	Icarus Verilog
$end
$timescale
	1s
$end
$scope module q2_tb $end
$var wire 1 ! y $end
$var reg 1 " a $end
$var reg 1 # b $end
$var reg 1 $ c $end
$var reg 1 % d $end
$scope module uut $end
$var wire 1 " a $end
$var wire 1 # b $end
$var wire 1 $ c $end
$var wire 1 % d $end
$var wire 1 ! y $end
$upscope $end
$upscope $end
$enddefinitions $end
#0
$dumpvars
0%
0$
0#
0"
1!
$end
#5
1%
#10
0%
1$
#15
1%
#20
0%
0$
1#
#25
1%
#30
0%
1$
#35
1%
#40
0%
0$
0#
1"
#45
1%
#50
0%
1$
#55
1%
#60
0%
0$
1#
#65
1%
#70
0%
1$
#75
0!
1%
