2023kuec2016/lab2/full_subtractor.v
module full_subtractor (
    input a,
    input b,
    input borrow_in,
    output y,
    output borrow_out
);

assign y = a ^ borrow_in ^ b;
assign borrow_out = (borrow_in & ~(a ^ b)) | (~a & b);

endmodule

2023kuec2016/SarthakSinghTariyal_2023kuec2016_lab2/full_subtractor_tb.v
`include "full_subtractor.v"

module full_subtractor_tb;

reg a, b, borrow_in;
wire y, borrow_out;

full_subtractor uut (
    .a(a),
    .b(b),
    .borrow_in(borrow_in),
    .y(y),
    .borrow_out(borrow_out)
);

initial begin
    a = 0; b = 0; borrow_in = 0; #5;
    a = 0; b = 0; borrow_in = 1; #5;
    a = 0; b = 1; borrow_in = 0; #5;
    a = 0; b = 1; borrow_in = 1; #5;
    a = 1; b = 0; borrow_in = 0; #5;
    a = 1; b = 0; borrow_in = 1; #5;
    a = 1; b = 1; borrow_in = 0; #5;
    a = 1; b = 1; borrow_in = 1; #5;
    $finish;
end

initial begin
    $dumpfile("full_subtractor.vcd");
    $dumpvars(0, full_subtractor_tb);
end

endmodule

2023kuec2016/lab2/full_subtractor.vcd
$date
	Wed Sep 11 10:54:14 2024
$end
$version
	Icarus Verilog
$end
$timescale
	1s
$end
$scope module full_subtractor_tb $end
$var wire 1 ! y $end
$var wire 1 " borrow_out $end
$var reg 1 # a $end
$var reg 1 $ b $end
$var reg 1 % borrow_in $end
$scope module uut $end
$var wire 1 # a $end
$var wire 1 $ b $end
$var wire 1 % borrow_in $end
$var wire 1 " borrow_out $end
$var wire 1 ! y $end
$upscope $end
$upscope $end
$enddefinitions $end
#0
$dumpvars
0%
0$
0#
0"
0!
$end
#5
1!
1"
1%
#10
1!
0%
1$
#15
0!
1%
#20
0"
1!
0%
0$
1#
#25
0!
1%
#30
0!
0%
1$
#35
1!
1"
1%
