2023kuec2016/lab2/q1.v
module q1 (
    input a,b,c,d,
    output y
);

assign y = (~a & ~b) | (~c & ~d);

endmodule

2023kuec2016/SarthakSinghTariyal_2023kuec2016_lab2/q1_tb.v
`include "q1.v"

module q1_tb;

reg a, b, c, d;
wire y;

q1 uut (
    .a(a),
    .b(b),
    .c(c),
    .d(d),
    .y(y)
);

initial begin
    a=0;b=0;c=0;d=0;#5;
    a=0;b=0;c=0;d=1;#5; 
    a=0;b=0;c=1;d=0;#5;    
    a=0;b=0;c=1;d=1;#5;    
    a=0;b=1;c=0;d=0;#5;    
    a=0;b=1;c=0;d=1;#5;    
    a=0;b=1;c=1;d=0;#5;    
    a=0;b=1;c=1;d=1;#5;    
    a=1;b=0;c=0;d=0;#5;    
    a=1;b=0;c=0;d=1;#5;    
    a=1;b=0;c=1;d=0;#5;    
    a=1;b=0;c=1;d=1;#5;    
    a=1;b=1;c=0;d=0;#5;    
    a=1;b=1;c=0;d=1;#5;    
    a=1;b=1;c=1;d=0;#5;    
    a=1;b=1;c=1;d=1;#5;    
    $finish;
end

initial begin
    $dumpfile("q1.vcd");
    $dumpvars(0, q1_tb);
end

endmodule

2023kuec2016/lab2/q1.vcd
$date
	Wed Sep 11 11:30:41 2024
$end
$version
	Icarus Verilog
$end
$timescale
	1s
$end
$scope module q1_tb $end
$var wire 1 ! y $end
$var reg 1 " a $end
$var reg 1 # b $end
$var reg 1 $ c $end
$var reg 1 % d $end
$scope module uut $end
$var wire 1 " a $end
$var wire 1 # b $end
$var wire 1 $ c $end
$var wire 1 % d $end
$var wire 1 ! y $end
$upscope $end
$upscope $end
$enddefinitions $end
#0
$dumpvars
0%
0$
0#
0"
1!
$end
#5
1%
#10
0%
1$
#15
1%
#20
0%
0$
1#
#25
0!
1%
#30
0%
1$
#35
1%
#40
1!
0%
0$
0#
1"
#45
0!
1%
#50
0%
1$
#55
1%
#60
1!
0%
0$
1#
#65
0!
1%
#70
0%
1$
#75
1%
