2023kuec2016/SarthakSinghTariyal_2023kuec2016_lab3/exp1/exp1.v
module exp1(a,b,c,d,y);
    input a,b,c,d;
    output y;
    assign y = (a || b) && (c || d);
endmodule

2023kuec2016/SarthakSinghTariyal_2023kuec2016_lab3/exp1/exp1_tb.v
`include "exp1.v"

module exp1_tb;
    reg a,b,c,d;
    wire y;
    
    exp1 exp1_uut(
        .a(a), .b(b), .c(c), .d(d), .y(y)
    );

    integer vars = 4;
    initial begin
        for (integer i = 0 ; i < 2**vars ; i += 1) begin
            a = (i / 2**(vars-1)) % 2;
            b = (i / 2**(vars-2)) % 2;
            c = (i / 2**(vars-3)) % 2;
            d = (i / 2**(vars-4)) % 2;
            #5;
        end
        $finish;
    end

    initial begin
        $dumpfile("exp1.vcd");
        $dumpvars(0, exp1_tb);
    end

endmodule

2023kuec2016/SarthakSinghTariyal_2023kuec2016_lab3/exp1/exp1.vcd
$date
	Wed Oct  9 11:43:33 2024
$end
$version
	Icarus Verilog
$end
$timescale
	1s
$end
$scope module exp1_tb $end
$var wire 1 ! y $end
$var reg 1 " a $end
$var reg 1 # b $end
$var reg 1 $ c $end
$var reg 1 % d $end
$var integer 32 & vars [31:0] $end
$scope module exp1_uut $end
$var wire 1 " a $end
$var wire 1 # b $end
$var wire 1 $ c $end
$var wire 1 % d $end
$var wire 1 ! y $end
$upscope $end
$scope begin $ivl_for_loop0 $end
$var integer 32 ' i [31:0] $end
$upscope $end
$upscope $end
$enddefinitions $end
#0
$dumpvars
b0 '
b100 &
0%
0$
0#
0"
0!
$end
#5
1%
b1 '
#10
0%
1$
b10 '
#15
1%
b11 '
#20
0%
0$
1#
b100 '
#25
1!
1%
b101 '
#30
0%
1$
b110 '
#35
1%
b111 '
#40
0!
0%
0$
0#
1"
b1000 '
#45
1!
1%
b1001 '
#50
0%
1$
b1010 '
#55
1%
b1011 '
#60
0!
0%
0$
1#
b1100 '
#65
1!
1%
b1101 '
#70
0%
1$
b1110 '
#75
1%
b1111 '
#80
b10000 '
