2023kuec2016/SarthakSinghTariyal_2023kuec2016_lab3/exp3/exp3.v
module exp3(a,b,c,y);
    input a,b,c;
    output y;
    assign y = (a && b && c) || (a && ~b && c) || (~a && b && c) || (~a && ~b && c);
endmodule

2023kuec2016/lab3/exp3/exp3_tb.v
`include "exp3.v"

module exp3_tb;
    reg a,b,c;
    wire y;
    
    exp3 exp3_uut(
        .a(a), .b(b), .c(c), .y(y)
    );

    integer vars = 3;
    initial begin
        for (integer i = 0 ; i < 2**vars ; i += 1) begin
            a = (i / 2**(vars-1)) % 2;
            b = (i / 2**(vars-2)) % 2;
            c = (i / 2**(vars-3)) % 2;
            #5;
        end
        $finish;
    end

    initial begin
        $dumpfile("SarthakSinghTariyal_2023kuec2016_lab3_expression3.vcd");
        $dumpvars(0, exp3_tb);
    end

endmodule

2023kuec2016/lab3/exp3/SarthakSinghTariyal_2023kuec2016_lab3_expression3.vcd
$date
	Wed Oct  9 10:56:33 2024
$end
$version
	Icarus Verilog
$end
$timescale
	1s
$end
$scope module exp3_tb $end
$var wire 1 ! y $end
$var reg 1 " a $end
$var reg 1 # b $end
$var reg 1 $ c $end
$var integer 32 % vars [31:0] $end
$scope module exp3_uut $end
$var wire 1 " a $end
$var wire 1 # b $end
$var wire 1 $ c $end
$var wire 1 ! y $end
$upscope $end
$scope begin $ivl_for_loop0 $end
$var integer 32 & i [31:0] $end
$upscope $end
$upscope $end
$enddefinitions $end
#0
$dumpvars
b0 &
b11 %
0$
0#
0"
0!
$end
#5
1!
1$
b1 &
#10
0!
0$
1#
b10 &
#15
1!
1$
b11 &
#20
0!
0$
0#
1"
b100 &
#25
1!
1$
b101 &
#30
0!
0$
1#
b110 &
#35
1!
1$
b111 &
#40
b1000 &
